magic_commit/__init__.py
magic_commit/__main__.py
magic_commit/config.py
magic_commit/magic_commit.py
magic_commit/templates/final.jinja
magic_commit/templates/system.jinja
magic_commit/templates/user.jinja
magic_commit/tests/__init__.py
magic_commit/tests/test_config.py
magic_commit/tests/test_magic_commit.py
magic_commit-0.6.2.dist-info/METADATA
magic_commit-0.6.2.dist-info/WHEEL
magic_commit-0.6.2.dist-info/entry_points.txt
magic_commit-0.6.2.dist-info/top_level.txt
magic_commit-0.6.2.dist-info/RECORD
