Metadata-Version: 2.1
Name: magic-commit
Version: 0.6.2
Summary: Generate commit messages with OpenAI\’s GPT.
Home-page: https://github.com/heyodai/magic-commit
Author: Odai Athamneh
Author-email: heyodai@gmail.com
License: UNKNOWN
Platform: UNKNOWN
Requires-Dist: openai
Requires-Dist: jinja2
Requires-Dist: dagwood
Requires-Dist: pyperclip
